audiblelight/__init__.py
audiblelight/ambience.py
audiblelight/augmentation.py
audiblelight/class_mappings.py
audiblelight/config.py
audiblelight/core.py
audiblelight/custom_types.py
audiblelight/download_data.py
audiblelight/event.py
audiblelight/micarrays.py
audiblelight/synthesize.py
audiblelight/utils.py
audiblelight/worldstate.py
resources/mp3d_material_config.json
scripts/download_data/download_fma.py
scripts/download_data/download_fsd.py
scripts/download_data/download_gibson.py
scripts/download_data/download_gibson_waypoints.py
scripts/download_data/download_rirs.py
scripts/download_data/utils.py
scripts/experiments/music_doa.py
scripts/generate/benchmark.py
scripts/generate/convert_to_dcase_format.py
scripts/generate/generate_with_random_events.py
scripts/get_eigenmike64_coordinates.py
scripts/seld/generate_dataset.py
scripts/seld/seld_dataset_assets.py
scripts/ssseg/generate_dataset.py
audiblelight-0.1.1.dist-info/METADATA
audiblelight-0.1.1.dist-info/WHEEL
audiblelight-0.1.1.dist-info/RECORD
