Metadata-Version: 2.4
Name: audiblelight
Version: 0.1.1
Summary: A controllable, end-to-end API for soundscape synthesis across ray-traced & real-world measured acoustics
License: CC-BY-4.0
Keywords: audio,sound,soundscape,environmental,ambisonics,microphone array,sound event detection,localization
Author: Huw Cheston
Author-email: h.cheston@qmul.ac.uk
Requires-Python: >=3.10,<4.0
Classifier: Development Status :: 4 - Beta
Classifier: Intended Audience :: Developers
Classifier: Intended Audience :: Science/Research
Classifier: License :: Other/Proprietary License
Classifier: Programming Language :: Python
Classifier: Programming Language :: Python :: 3
Classifier: Programming Language :: Python :: 3.10
Classifier: Programming Language :: Python :: 3.11
Classifier: Programming Language :: Python :: 3.12
Classifier: Programming Language :: Python :: 3.13
Classifier: Programming Language :: Python :: 3.14
Classifier: Topic :: Multimedia :: Sound/Audio :: Analysis
Classifier: Topic :: Multimedia :: Sound/Audio :: Sound Synthesis
Requires-Dist: deepdiff
Requires-Dist: gdown
Requires-Dist: librosa (==0.11.0)
Requires-Dist: loguru
Requires-Dist: matplotlib
Requires-Dist: numpy (==2.0.2)
Requires-Dist: pandas (==2.2.2)
Requires-Dist: pedalboard (==0.9.17)
Requires-Dist: pillow (==11.2.1)
Requires-Dist: plotly (==5.24.1)
Requires-Dist: pyroomacoustics
Requires-Dist: pysofaconventions
Requires-Dist: rlr-audio-propagation (==0.0.1)
Requires-Dist: rtree (==1.4.0)
Requires-Dist: scipy
Requires-Dist: soundfile
Requires-Dist: torch
Requires-Dist: tqdm (==4.67.1)
Requires-Dist: trimesh (==4.6.11)
Project-URL: Homepage, https://github.com/AudibleLight/AudibleLight
Project-URL: Repository, https://github.com/AudibleLight/AudibleLight
